flayout/__init__.py
flayout/_nbdev.py
flayout/bokeh.py
flayout/cell.py
flayout/example_lib.py
flayout/factories.py
flayout/gui.py
flayout/io.py
flayout/layers.lyp
flayout/notebook.py
flayout/pcell.py
flayout-0.0.1.dist-info/LICENSE
flayout-0.0.1.dist-info/METADATA
flayout-0.0.1.dist-info/WHEEL
flayout-0.0.1.dist-info/top_level.txt
flayout-0.0.1.dist-info/RECORD
