Metadata-Version: 2.1
Name: flayout
Version: 0.0.1
Summary: Thin functional/declarative wrapper around the KLayout Python API
Home-page: https://gitlab.com/flaport/flayout
Author: Floris Laporte
Author-email: floris.laporte@gmail.com
Classifier: Development Status :: 3 - Alpha
Classifier: License :: OSI Approved :: GNU General Public License v3 (GPLv3)
Classifier: Operating System :: OS Independent
Classifier: Programming Language :: Python :: 3
Classifier: Topic :: Scientific/Engineering
License-File: LICENSE
Requires-Dist: klayout
Provides-Extra: dev
Requires-Dist: black ; extra == 'dev'
Requires-Dist: bokeh ; extra == 'dev'
Requires-Dist: bump2version ; extra == 'dev'
Requires-Dist: ipykernel ; extra == 'dev'
Requires-Dist: isort ; extra == 'dev'
Requires-Dist: lxml ; extra == 'dev'
Requires-Dist: nbdev ; extra == 'dev'
Requires-Dist: nbstripout ; extra == 'dev'
Requires-Dist: numpy ; extra == 'dev'
Requires-Dist: papermill ; extra == 'dev'
Requires-Dist: pre-commit ; extra == 'dev'
Requires-Dist: pytest ; extra == 'dev'
Requires-Dist: pyyaml ; extra == 'dev'
Requires-Dist: tqdm ; extra == 'dev'
